matlab_kernel/__init__.py
matlab_kernel/__main__.py
matlab_kernel/check.py
matlab_kernel/kernel.py
matlab_kernel/kernel_template.json
matlab_kernel/matlab/kernel.json
matlab_kernel/matlab_connect/kernel.json
matlab_kernel-0.17.1.data/data/share/jupyter/kernels/matlab/kernel.json
matlab_kernel-0.17.1.data/data/share/jupyter/kernels/matlab_connect/kernel.json
matlab_kernel-0.17.1.dist-info/LICENSE.txt
matlab_kernel-0.17.1.dist-info/METADATA
matlab_kernel-0.17.1.dist-info/WHEEL
matlab_kernel-0.17.1.dist-info/top_level.txt
matlab_kernel-0.17.1.dist-info/RECORD
