Metadata-Version: 2.1
Name: matlab-kernel
Version: 0.17.1
Summary: UNKNOWN
Home-page: https://github.com/Calysto/matlab_kernel
Author: Steven Silvester, Antony Lee
License: BSD
Platform: UNKNOWN
Classifier: Framework :: IPython
Classifier: License :: OSI Approved :: BSD License
Classifier: Programming Language :: Python :: 3.4
Classifier: Programming Language :: Python :: 3.5
Classifier: Topic :: System :: Shells
Requires: metakernel (>0.23.0)
Requires: jupyter_client (>=4.4.0)
Requires: ipython (>=4.0.0)
License-File: LICENSE.txt
Requires-Dist: metakernel (>=0.23.0)
Requires-Dist: jupyter-client (>=4.4.0)
Requires-Dist: ipython (>=4.0.0)
Requires-Dist: wurlitzer (>=1.0.2) ; platform_system != "Windows"
Requires-Dist: backports.tempfile ; python_version < "3.0"
